secrules_parsing/__init__.py
secrules_parsing/cli.py
secrules_parsing/model/__init__.py
secrules_parsing/model/secrules.tx
secrules_parsing/parser.py
secrules_parsing/resources.py
secrules_parsing-0.2.14.dist-info/METADATA
secrules_parsing-0.2.14.dist-info/WHEEL
secrules_parsing-0.2.14.dist-info/entry_points.txt
secrules_parsing-0.2.14.dist-info/licenses/LICENSE
secrules_parsing-0.2.14.dist-info/RECORD
