Metadata-Version: 2.4
Name: secrules-parsing
Version: 0.2.14
Summary: ModSecurity DSL Parser package using textX
License: Apache-2.0
License-File: LICENSE
Keywords: secrule,modsecurity,parser,textX
Author: Felipe Zipitria
Author-email: felipe.zipitria@owasp.org
Requires-Python: >=3.7,<4.0
Classifier: License :: OSI Approved :: Apache Software License
Classifier: License :: OSI Approved :: MIT License
Classifier: Operating System :: OS Independent
Classifier: Programming Language :: Python :: 3
Classifier: Programming Language :: Python :: 3.7
Classifier: Programming Language :: Python :: 3.8
Classifier: Programming Language :: Python :: 3.9
Classifier: Programming Language :: Python :: 3.10
Classifier: Programming Language :: Python :: 3.11
Classifier: Programming Language :: Python :: 3.12
Classifier: Programming Language :: Python :: 3.13
Classifier: Programming Language :: Python :: 3.14
Requires-Dist: importlib-metadata (>=4.11.3,<7.0.0)
Requires-Dist: textX (>=2.3,<4.0)
Project-URL: Bug Tracker, https://github.com/coreruleset/secrules_parsing/issues
Project-URL: Documentation, https://github.com/coreruleset/secrules_parsing
Project-URL: Homepage, https://github.com/coreruleset/secrules_parsing
Project-URL: Repository, https://github.com/coreruleset/secrules_parsing
